bakrialtaif_faq/__init__.py
bakrialtaif_faq/divide.py
bakrialtaif_faq/multiply.py
bakrialtaif_faq-0.1.0.dist-info/LICENSE.txt
bakrialtaif_faq-0.1.0.dist-info/METADATA
bakrialtaif_faq-0.1.0.dist-info/WHEEL
bakrialtaif_faq-0.1.0.dist-info/top_level.txt
bakrialtaif_faq-0.1.0.dist-info/RECORD
